{
  "id": "seedhammer",
  "name": "Seedhammer",
  "purchasable": true,
  "basic-information": {
    "price": {
      "value": "$599"
    },
    "amazon": {
      "supported": false
    }
  },
  "company": {
    "brand": {
      "value": "Seedhammer"
    },
    "headquarters": {
      "value": "-"
    },
    "website": {
      "value": "seedhammer.com",
      "url": "https://seedhammer.com/"
    },
    "blog": {
      "value": "seedhammer.com/article",
      "url": "https://seedhammer.com/article/"
    },
    "twitter": {
      "value": "@SeedHammer",
      "url": "https://twitter.com/SeedHammer"
    },
    "nostr": {
      "value": "-"
    },
    "youtube": {
      "value": "@SeedHammer",
      "url": "https://www.youtube.com/@SeedHammer"
    }
  },
  "payment-methods": {
    "btc-on-chain": {
      "value": "YES (via BTCPay)",
      "flag": "positive",
      "supported": true
    },
    "btc-lightning": {
      "value": "YES",
      "flag": "positive",
      "supported": true
    },
    "alt-coins": {
      "value": "NO",
      "supported": false
    },
    "credit-debit-card": {
      "value": "NO",
      "supported": false
    }
  },
  "size-materials": {
    "weight": {
      "value": "?"
    },
    "dimensions": {
      "value": "?"
    },
    "materials": {
      "value": "Stainless steel",
      "links": [
        {
          "title": "The SeedHammer Metal Plates",
          "url": "https://seedhammer.com/article/the-seedhammer-metal-plates"
        }
      ]
    },
    "water-proof": {
      "value": "YES",
      "flag": "positive",
      "supported": true
    },
    "fire-proof": {
      "value": "YES",
      "flag": "positive",
      "supported": true
    },
    "stress-tests": {
      "value": "-",
      "supported": false
    }
  },
  "security": {
    "pin-protection": {
      "value": "NO",
      "flag": "negative",
      "supported": false
    }
  },
  "backup-compatibility": {
    "output-descriptor": {
      "value": "YES",
      "flag": "positive",
      "supported": true
    },
    "bip39-12-words": {
      "value": "YES",
      "flag": "positive",
      "supported": true
    },
    "bip39-24-words": {
      "value": "YES",
      "flag": "positive",
      "supported": true
    },
    "shamir-backup": {
      "value": "NO",
      "flag": "negative",
      "supported": false
    },
    "hexadecimal-strings": {
      "value": "NO",
      "flag": "negative",
      "supported": false
    },
    "ascii-strings": {
      "value": "NO",
      "flag": "negative",
      "supported": false
    }
  }
}